Metadata-Version: 2.1
Name: carnoffel-code
Version: 0.2
Summary: Сильнейшее зло. Код хранящий самые страшные пороки людские. Он пораждает агрессию, с помощью которой достигает забвения. Если вы увидете его содержимое, то забвения вам уже не избежать.
Author-email: tirackot@gmail.com
